defydb.py
DefyDatabase-10.0.0a4.dev202307071900.dist-info/METADATA
DefyDatabase-10.0.0a4.dev202307071900.dist-info/WHEEL
DefyDatabase-10.0.0a4.dev202307071900.dist-info/top_level.txt
DefyDatabase-10.0.0a4.dev202307071900.dist-info/RECORD
