Metadata-Version: 2.1
Name: DefyDatabase
Version: 10.0.0a4.dev202307071900
Summary: Database for personal data based on SQLite
Author: Defymen
Author-email: vmuonline@126.com
Classifier: Development Status :: 3 - Alpha
Classifier: Programming Language :: Python :: 3
Classifier: License :: OSI Approved :: MIT License
Classifier: Operating System :: OS Independent
Requires-Python: >=3.6
